linear_cli/__init__.py
linear_cli/api.py
linear_cli/auth.py
linear_cli/cli.py
linear_cli/config.py
linear_cli/models.py
linear_app_cli-0.1.2.dist-info/METADATA
linear_app_cli-0.1.2.dist-info/WHEEL
linear_app_cli-0.1.2.dist-info/entry_points.txt
linear_app_cli-0.1.2.dist-info/licenses/LICENSE
linear_app_cli-0.1.2.dist-info/RECORD
